[{"Name": "Japanese encephalitis virus vaccine Nakayama-NIH strain, inactivated", "RXCUI": "1300779", "TTY": "PIN", "SCDCs": [{"Name": "Japanese encephalitis virus vaccine Nakayama-NIH strain, inactivated 0.012 MG/ML", "RXCUI": "1300780", "TTY": "SCDC", "SCDs": [{"Name": "0.5 ML Japanese encephalitis virus vaccine Nakayama-NIH strain, inactivated 0.012 MG/ML Prefilled Syringe", "RXCUI": "1300781", "TTY": "SCD", "SBDs": [{"Name": "0.5 ML Japanese encephalitis virus vaccine Nakayama-NIH strain, inactivated 0.012 MG/ML Prefilled Syringe [Ixiaro]", "RXCUI": "1300783", "TTY": "SBD", "NDCs": ["42515000201", "62195005101"], "BNs": [{"Name": "Ixiaro", "RXCUI": "845529", "TTY": "BN"}]}]}]}], "UNII": "DZ854I04ZE"}, {"Name": "Japanese encephalitis virus vaccine, inactivated", "RXCUI": "845525", "TTY": "IN", "SCDCs": [{"Name": "Japanese encephalitis virus vaccine Nakayama-NIH strain, inactivated 0.012 MG/ML", "RXCUI": "1300780", "TTY": "SCDC", "SCDs": [{"Name": "0.5 ML Japanese encephalitis virus vaccine Nakayama-NIH strain, inactivated 0.012 MG/ML Prefilled Syringe", "RXCUI": "1300781", "TTY": "SCD", "SBDs": [{"Name": "0.5 ML Japanese encephalitis virus vaccine Nakayama-NIH strain, inactivated 0.012 MG/ML Prefilled Syringe [Ixiaro]", "RXCUI": "1300783", "TTY": "SBD", "NDCs": ["42515000201", "62195005101"], "BNs": [{"Name": "Ixiaro", "RXCUI": "845529", "TTY": "BN"}]}]}]}]}, {"Name": "Johnson grass pollen extract", "RXCUI": "852136", "TTY": "IN", "SCDCs": [{"Name": "Johnson grass pollen extract 100 MG/ML", "RXCUI": "889670", "TTY": "SCDC", "SCDs": [{"Name": "Johnson grass pollen extract 100 MG/ML Injectable Solution", "RXCUI": "889671", "TTY": "SCD", "NDCs": ["00268121410", "00268121450", "22840124302", "65044174702", "65044174703", "65044174704"]}]}, {"Name": "Johnson grass pollen extract 40000 UNT/ML", "RXCUI": "889663", "TTY": "SCDC", "SCDs": [{"Name": "Johnson grass pollen extract 40000 UNT/ML Injectable Solution", "RXCUI": "889664", "TTY": "SCD", "NDCs": ["00268121650"]}]}, {"Name": "Johnson grass pollen extract 50 MG/ML", "RXCUI": "852137", "TTY": "SCDC", "SCDs": [{"Name": "Johnson grass pollen extract 50 MG/ML Injectable Solution", "RXCUI": "852139", "TTY": "SCD", "NDCs": ["00268121510", "00268121550", "00268662906", "22840520502", "22840520504", "22840520505", "49643041305", "49643041310", "49643041330", "49643041350", "65044174402", "65044174403", "65044174404", "65044174501"]}]}], "UNII": "577VA5B4HP"}, {"Name": "Johnson grass smut allergenic extract", "RXCUI": "852128", "TTY": "IN", "SCDCs": [{"Name": "Johnson grass smut allergenic extract 50 MG/ML", "RXCUI": "2103303", "TTY": "SCDC", "SCDs": [{"Name": "Bermuda grass smut allergenic extract 50 MG/ML / Johnson grass smut allergenic extract 50 MG/ML Injectable Solution", "RXCUI": "1232665", "TTY": "SCD", "NDCs": ["22840967102", "22840967104", "22840967105", "22840967602"]}, {"Name": "Johnson grass smut allergenic extract 50 MG/ML Injectable Solution", "RXCUI": "852131", "TTY": "SCD", "NDCs": ["22840565002", "22840565004", "22840565005", "49643012305", "49643012310", "49643012330", "49643012350"]}]}], "UNII": "GQM6LVU5V8"}, {"Name": "jute fiber allergenic extract", "RXCUI": "852412", "TTY": "IN", "SCDCs": [{"Name": "jute fiber allergenic extract 100 MG/ML", "RXCUI": "852413", "TTY": "SCDC", "SCDs": [{"Name": "jute fiber allergenic extract 100 MG/ML Injectable Solution", "RXCUI": "852415", "TTY": "SCD", "NDCs": ["49643001605", "49643001610", "49643001630", "49643001650"]}]}], "UNII": "TVA75O7S63"}]